setup.py
kd_infra/__init__.py
kd_infra.egg-info/PKG-INFO
kd_infra.egg-info/SOURCES.txt
kd_infra.egg-info/dependency_links.txt
kd_infra.egg-info/top_level.txt
kd_infra/app/__init__.py
kd_infra/app/redis_pool.py
kd_infra/base/__init__.py
kd_infra/base/base_http.py
kd_infra/base/log.py
kd_infra/base/opt.py
kd_infra/base/singleton.py
kd_infra/base/timer.py
kd_infra/base/tools.py
kd_infra/hadoop/__init__.py
kd_infra/hadoop/hadoopTools.py
kd_infra/hadoop/hdfs_util.py
kd_infra/hbase/__init__.py