Metadata-Version: 1.0
Name: kd-infra
Version: 1.0
Summary: Custom script
Home-page: https://github.com/duquan640/pip_kd/kd_infra
Author: dq
Author-email: duquan@kuandeng.com
License: MIT Licence
Keywords: pip,infra,featureextraction
Platform: any
